liffylights2.py
setup.cfg
setup.py
liffylights2.egg-info/PKG-INFO
liffylights2.egg-info/SOURCES.txt
liffylights2.egg-info/dependency_links.txt
liffylights2.egg-info/top_level.txt