Metadata-Version: 1.1
Name: liffylights2
Version: 0.1.0
Summary: LIFX Python library
Home-page: https://github.com/keatontaylor/liffylights2
Author: Keaton Taylor
Author-email: keatonstaylor@gmail.com
License: MIT
Keywords: homeassistant
Platform: UNKNOWN
Classifier: Development Status :: 4 - Beta
Classifier: Intended Audience :: Developers
Classifier: License :: OSI Approved :: MIT License
Classifier: Operating System :: Microsoft :: Windows
Classifier: Operating System :: POSIX :: Linux
Classifier: Programming Language :: Python :: 3 :: Only
Classifier: Topic :: Software Development :: Libraries :: Python Modules
